traceai_portkey/__init__.py
traceai_portkey/_request_attributes_extractor.py
traceai_portkey/_response_attributes_extractor.py
traceai_portkey/_utils.py
traceai_portkey/_with_span.py
traceai_portkey/_wrappers.py
traceai_portkey/version.py
traceai_portkey-0.1.1.dist-info/METADATA
traceai_portkey-0.1.1.dist-info/WHEEL
traceai_portkey-0.1.1.dist-info/RECORD
